README.md
setup.py
singer/__init__.py
singer/cache.py
singer/config.py
singer/logger.py
singer/main.py
singer/thread.py
singer/utils.py
singer.egg-info/PKG-INFO
singer.egg-info/SOURCES.txt
singer.egg-info/dependency_links.txt
singer.egg-info/not-zip-safe
singer.egg-info/top_level.txt