Metadata-Version: 1.2
Name: singer
Version: 0.1.1
Summary: singer script
Home-page: https://github.com/shoy160/python-singer
Author: shay
Author-email: shoy160@qq.com
License: UNKNOWN
Platform: UNKNOWN
Requires-Python: >=3.6
